[
  {
    "repo": "AscendAI",
    "stars": 14,
    "forks": 3,
    "watchers": 1,
    "open_issues": 0,
    "language": "Python",
    "size_kb": 1626328,
    "default_branch": "master",
    "updated_at": "2025-07-02T03:46:03Z",
    "clones": 2969,
    "uniques": 204,
    "views": 2841,
    "visitors": 30,
    "pulls_count": 0,
    "fetched": "2025-07-02T10:00:29.274325"
  },
  {
    "repo": "Mobile-Developer",
    "stars": 4,
    "forks": 0,
    "watchers": 1,
    "open_issues": 0,
    "language": "Python",
    "size_kb": 25887,
    "default_branch": "master",
    "updated_at": "2025-07-01T21:28:14Z",
    "clones": 118,
    "uniques": 84,
    "views": 354,
    "visitors": 3,
    "pulls_count": 0,
    "fetched": "2025-07-02T10:00:29.675827"
  },
  {
    "repo": "AscendDocs-of-GovSeverance",
    "stars": 2,
    "forks": 0,
    "watchers": 0,
    "open_issues": 0,
    "language": null,
    "size_kb": 3879,
    "default_branch": "master",
    "updated_at": "2025-07-01T22:55:23Z",
    "clones": 347,
    "uniques": 184,
    "views": 1094,
    "visitors": 4,
    "pulls_count": 0,
    "fetched": "2025-07-02T10:00:30.067843"
  },
  {
    "repo": "GodCore",
    "stars": 4,
    "forks": 0,
    "watchers": 1,
    "open_issues": 0,
    "language": "Python",
    "size_kb": 26702,
    "default_branch": "master",
    "updated_at": "2025-07-01T21:28:38Z",
    "clones": 30,
    "uniques": 24,
    "views": 151,
    "visitors": 24,
    "pulls_count": 0,
    "fetched": "2025-07-02T10:00:30.414980"
  },
  {
    "repo": "AscendNet",
    "stars": 5,
    "forks": 0,
    "watchers": 0,
    "open_issues": 0,
    "language": null,
    "size_kb": 185,
    "default_branch": "master",
    "updated_at": "2025-07-01T21:24:23Z",
    "clones": 72,
    "uniques": 53,
    "views": 217,
    "visitors": 1,
    "pulls_count": 0,
    "fetched": "2025-07-02T10:00:30.786609"
  },
  {
    "repo": "WorkFlowRepo",
    "stars": 1,
    "forks": 0,
    "watchers": 0,
    "open_issues": 0,
    "language": null,
    "size_kb": 363767,
    "default_branch": "master",
    "updated_at": "2025-07-02T09:50:31Z",
    "clones": 158,
    "uniques": 68,
    "views": 387,
    "visitors": 1,
    "pulls_count": 0,
    "fetched": "2025-07-02T10:00:31.193883"
  }
]